xblocks_contrib/__init__.py
xblocks_contrib/test_settings.py
xblocks_contrib/annotatable/__init__.py
xblocks_contrib/annotatable/annotatable.py
xblocks_contrib/annotatable/static/css/annotatable.css
xblocks_contrib/annotatable/static/css/annotatable_editor.css
xblocks_contrib/annotatable/static/js/src/annotatable.js
xblocks_contrib/annotatable/static/js/src/annotatable_editor.js
xblocks_contrib/annotatable/templates/annotatable.html
xblocks_contrib/annotatable/templates/annotatable_editor.html
xblocks_contrib/common/__init__.py
xblocks_contrib/common/xml_utils.py
xblocks_contrib/discussion/__init__.py
xblocks_contrib/discussion/discussion.py
xblocks_contrib/discussion/static/css/discussion.css
xblocks_contrib/discussion/static/js/src/discussion.js
xblocks_contrib/discussion/templates/discussion.html
xblocks_contrib/html/__init__.py
xblocks_contrib/html/html.py
xblocks_contrib/html/static/css/html.css
xblocks_contrib/html/templates/html/announcement.yaml
xblocks_contrib/html/templates/html/anon_user_id.yaml
xblocks_contrib/html/templates/html/iframe.yaml
xblocks_contrib/html/templates/html/raw.yaml
xblocks_contrib/html/templates/html/zooming_image.yaml
xblocks_contrib/lti/__init__.py
xblocks_contrib/lti/lti.py
xblocks_contrib/lti/lti_2_util.py
xblocks_contrib/lti/static/README.txt
xblocks_contrib/lti/static/css/lti.css
xblocks_contrib/lti/static/js/src/lti.js
xblocks_contrib/lti/templates/lti.html
xblocks_contrib/lti/templates/lti_form.html
xblocks_contrib/poll/__init__.py
xblocks_contrib/poll/poll.py
xblocks_contrib/poll/static/css/poll.css
xblocks_contrib/poll/static/js/src/poll.js
xblocks_contrib/poll/templates/poll.html
xblocks_contrib/problem/__init__.py
xblocks_contrib/problem/problem.py
xblocks_contrib/problem/static/css/problem.css
xblocks_contrib/problem/static/js/src/problem.js
xblocks_contrib/problem/templates/problem.html
xblocks_contrib/video/__init__.py
xblocks_contrib/video/exceptions.py
xblocks_contrib/video/video.py
xblocks_contrib-0.10.1.dist-info/licenses/LICENSE.txt
xblocks_contrib-0.10.1.dist-info/METADATA
xblocks_contrib-0.10.1.dist-info/WHEEL
xblocks_contrib-0.10.1.dist-info/entry_points.txt
xblocks_contrib-0.10.1.dist-info/top_level.txt
xblocks_contrib-0.10.1.dist-info/RECORD
