Metadata-Version: 2.4
Name: xblocks-contrib
Version: 0.10.1
Summary: core xblocks
Home-page: https://github.com/openedx/xblocks-contrib
Author: Open edX Project
Author-email: oscm@openedx.org
License: AGPL 3.0
Keywords: Python edx
Classifier: Development Status :: 3 - Alpha
Classifier: Intended Audience :: Developers
Classifier: License :: OSI Approved :: GNU Affero General Public License v3 or later (AGPLv3+)
Classifier: Natural Language :: English
Classifier: Programming Language :: Python :: 3
Classifier: Programming Language :: Python :: 3.11
Classifier: Programming Language :: Python :: 3.12
Requires-Python: >=3.11
License-File: LICENSE.txt
Requires-Dist: XBlock
Requires-Dist: django-statici18n
Requires-Dist: edx-i18n-tools
Requires-Dist: edx-opaque-keys
Requires-Dist: nh3
Requires-Dist: oauthlib
Requires-Dist: openedx-django-pyfs
Dynamic: author
Dynamic: author-email
Dynamic: classifier
Dynamic: description
Dynamic: home-page
Dynamic: keywords
Dynamic: license
Dynamic: license-file
Dynamic: requires-dist
Dynamic: requires-python
Dynamic: summary
